{
    "z 90 on the air testing": [
        "Z (90), -- \"On the Air\" Testing",
        "z (90), -- \"On the Air\" Testing"
    ],
    "z 90 on the air testin": [
        "Z (90), -- \"On the Air\" Testing",
        "z (90), -- \"On the Air\" Testing"
    ],
    "z 90 on the air testi": [
        "Z (90), -- \"On the Air\" Testing",
        "z (90), -- \"On the Air\" Testing"
    ],
    "z 90 on the air test": [
        "Z (90), -- \"On the Air\" Testing",
        "z (90), -- \"On the Air\" Testing"
    ],
    "z 90 on the air tes": [
        "Z (90), -- \"On the Air\" Testing",
        "z (90), -- \"On the Air\" Testing"
    ],
    "z 90 on the air te": [
        "Z (90), -- \"On the Air\" Testing",
        "z (90), -- \"On the Air\" Testing"
    ],
    "z 90 on the air t": [
        "Z (90), -- \"On the Air\" Testing",
        "z (90), -- \"On the Air\" Testing"
    ],
    "z 90 on the air": [
        "Z (90), -- \"On the Air\" Testing",
        "Z (90), -- \"On the Air\" Testing",
        "Z (90), -- \"On the Air\" Testing",
        "z (90), -- \"On the Air\" Testing",
        "z (90), -- \"On the Air\" Testing",
        "z (90), -- \"On the Air\" Testing"
    ],
    "z 90 on the ai": [
        "Z (90), -- \"On the Air\" Testing",
        "z (90), -- \"On the Air\" Testing"
    ],
    "z 90 on the a": [
        "Z (90), -- \"On the Air\" Testing",
        "z (90), -- \"On the Air\" Testing"
    ],
    "z 90 on the": [
        "Z (90), -- \"On the Air\" Testing",
        "Z (90), -- \"On the Air\" Testing",
        "z (90), -- \"On the Air\" Testing",
        "z (90), -- \"On the Air\" Testing"
    ],
    "z 90 on th": [
        "Z (90), -- \"On the Air\" Testing",
        "z (90), -- \"On the Air\" Testing"
    ],
    "z 90 on t": [
        "Z (90), -- \"On the Air\" Testing",
        "z (90), -- \"On the Air\" Testing"
    ],
    "z 90 on": [
        "Z (90), -- \"On the Air\" Testing",
        "Z (90), -- \"On the Air\" Testing",
        "z (90), -- \"On the Air\" Testing",
        "z (90), -- \"On the Air\" Testing"
    ],
    "z 90 o": [
        "Z (90), -- \"On the Air\" Testing",
        "z (90), -- \"On the Air\" Testing"
    ],
    "z 90": [
        "Z (90), -- \"On the Air\" Testing",
        "Z (90), -- \"On the Air\" Testing",
        "Z (90), -- \"On the Air\" Testing",
        "Z (90), -- \"On the Air\" Testing",
        "Z (90), -- \"On the Air\" Testing",
        "Z (90), -- \"On the Air\" Testing",
        "Z (90), -- \"On the Air\" Testing",
        "Z (90), -- \"On the Air\" Testing",
        "z (90), -- \"On the Air\" Testing",
        "z (90), -- \"On the Air\" Testing",
        "z (90), -- \"On the Air\" Testing",
        "z (90), -- \"On the Air\" Testing",
        "z (90), -- \"On the Air\" Testing",
        "z (90), -- \"On the Air\" Testing",
        "z (90), -- \"On the Air\" Testing",
        "z (90), -- \"On the Air\" Testing"
    ],
    "z 9": [
        "Z (90), -- \"On the Air\" Testing",
        "z (90), -- \"On the Air\" Testing"
    ],
    "z": [
        "Z (90), -- \"On the Air\" Testing",
        "Z (90), -- \"On the Air\" Testing",
        "Z (90), -- \"On the Air\" Testing",
        "z (90), -- \"On the Air\" Testing",
        "z (90), -- \"On the Air\" Testing",
        "z (90), -- \"On the Air\" Testing"
    ]
}